pylume-0.2.1.dist-info/METADATA
pylume-0.2.1.dist-info/WHEEL
pylume-0.2.1.dist-info/entry_points.txt
pylume/__init__.py
pylume/client.py
pylume/exceptions.py
pylume/lume
pylume/models.py
pylume/pylume.py
pylume/server.py
pylume-0.2.1.dist-info/RECORD
