Metadata-Version: 2.1
Name: pylume
Version: 0.2.1
Summary: Python SDK for lume - run macOS and Linux VMs on Apple Silicon
Keywords: macos,virtualization,vm,apple-silicon
Author-Email: TryCua <gh@trycua.com>
License: MIT
Classifier: Intended Audience :: Developers
Classifier: License :: OSI Approved :: MIT License
Classifier: Operating System :: MacOS :: MacOS X
Classifier: Programming Language :: Python :: 3
Classifier: Programming Language :: Python :: 3.10
Classifier: Programming Language :: Python :: 3.11
Classifier: Programming Language :: Python :: 3.12
Project-URL: homepage, https://github.com/trycua/pylume
Project-URL: repository, https://github.com/trycua/pylume
Requires-Python: >=3.9
Requires-Dist: pydantic>=2.11.1
